featq/__init__.py
featq/featq.py
featq-1.0.0.dist-info/METADATA
featq-1.0.0.dist-info/WHEEL
featq-1.0.0.dist-info/top_level.txt
featq-1.0.0.dist-info/RECORD
