Metadata-Version: 2.1
Name: featq
Version: 1.0.0
Summary: Feature Engineering with Q-learning
Home-page: UNKNOWN
Author: HJKIM
Author-email: 45683heejoo@naver.com
License: MIT
Platform: UNKNOWN
Requires-Python: >=3
Requires-Dist: pandas
Requires-Dist: numpy
Requires-Dist: xgboost
Requires-Dist: sklearn
Requires-Dist: scipy
Requires-Dist: lightgbm
